ytvideo2pdf/__init__.py
ytvideo2pdf/__main__.py
ytvideo2pdf/enums.py
ytvideo2pdf/main.py
ytvideo2pdf/extraction_strategy/__init__.py
ytvideo2pdf/extraction_strategy/base_extraction_strategy.py
ytvideo2pdf/extraction_strategy/extraction_strategy_factory.py
ytvideo2pdf/extraction_strategy/k_transactions_extraction_strategy.py
ytvideo2pdf/extraction_strategy/key_moments_extraction_strategy.py
ytvideo2pdf/extraction_strategy/prominent_peak_extraction_strategy.py
ytvideo2pdf/extraction_strategy/rate_change_threshold_strategy.py
ytvideo2pdf/extraction_strategy/timestamp_extraction_strategy.py
ytvideo2pdf/input_strategy/__init__.py
ytvideo2pdf/input_strategy/base.py
ytvideo2pdf/input_strategy/factory.py
ytvideo2pdf/input_strategy/local_file.py
ytvideo2pdf/input_strategy/pickle.py
ytvideo2pdf/input_strategy/youtube.py
ytvideo2pdf/ocr_approval/__init__.py
ytvideo2pdf/ocr_approval/approve_all.py
ytvideo2pdf/ocr_approval/base.py
ytvideo2pdf/ocr_approval/factory.py
ytvideo2pdf/ocr_approval/phash.py
ytvideo2pdf/ocr_approval/pixel_comparison.py
ytvideo2pdf/ocr_approval/reject_all.py
ytvideo2pdf/ocr_strategy/__init__.py
ytvideo2pdf/ocr_strategy/easy_ocr.py
ytvideo2pdf/ocr_strategy/ocr_strategy.py
ytvideo2pdf/ocr_strategy/ocr_strategy_factory.py
ytvideo2pdf/ocr_strategy/paddle_ocr.py
ytvideo2pdf/ocr_strategy/tesseract_ocr.py
ytvideo2pdf/utils/__init__.py
ytvideo2pdf/utils/constants.py
ytvideo2pdf/utils/data_plotter.py
ytvideo2pdf/utils/directory_manager.py
ytvideo2pdf/utils/file_frame.py
ytvideo2pdf/utils/frame.py
ytvideo2pdf/utils/helper.py
ytvideo2pdf/utils/image_utils.py
ytvideo2pdf/utils/post_processor.py
ytvideo2pdf/utils/processed_frame.py
ytvideo2pdf/utils/random_generator.py
ytvideo2pdf/utils/video_processor.py
ytvideo2pdf-0.0.15.dist-info/METADATA
ytvideo2pdf-0.0.15.dist-info/WHEEL
ytvideo2pdf-0.0.15.dist-info/licenses/LICENSE
ytvideo2pdf-0.0.15.dist-info/RECORD
