Metadata-Version: 2.4
Name: ytvideo2pdf
Version: 0.0.15
Summary: Convert YouTube educational video to crisp PDF notes
Project-URL: Homepage, https://github.com/DeveloperDowny/most_info_frame_extractor
Project-URL: Issues, https://github.com/DeveloperDowny/most_info_frame_extractor/issues
Author-email: Vedant Panchal <vedantpanchal12345@gmail.com>
License-Expression: MIT
License-File: LICENSE
Classifier: Operating System :: OS Independent
Classifier: Programming Language :: Python :: 3
Requires-Python: >=3.9
Requires-Dist: imagehash
Requires-Dist: matplotlib
Requires-Dist: numpy
Requires-Dist: opencv-python
Requires-Dist: pandas
Requires-Dist: pillow
Requires-Dist: pytesseract
Requires-Dist: pytubefix
Requires-Dist: sanitize-filename
Requires-Dist: scipy
Requires-Dist: tqdm
Requires-Dist: typer[all]
Provides-Extra: easyocr
Requires-Dist: easyocr; extra == 'easyocr'
Provides-Extra: paddleocr
Requires-Dist: paddleocr; extra == 'paddleocr'
Requires-Dist: paddlepaddle; extra == 'paddleocr'
